Metadata-Version: 1.1
Name: pyamdcovc
Version: 0.1.0
Summary: Control AMD GPUs using AMDCOVC utility
Home-page: https://hydra.ecd.space/eduard/pyamdcovc/
Author: Eduard Christian Dumitrescu
Author-email: eduard.c.dumitrescu@gmail.com
License: LGPLv3
Platform: UNKNOWN
Classifier: License :: OSI Approved :: GNU Lesser General Public License v3 (LGPLv3)
Classifier: Programming Language :: Python :: 3 :: Only
Classifier: Topic :: Software Development :: Libraries
